{"name":"Nhan Tổng Chúng Ta Kí Hợp Đồng Đi!","folder":"nhantongchungtakihopdjongdji","tacGia":"Phạm Tuyết Trinh","theLoai":"Ngôn Tình","trangThai":"Đang ra","description":"Tác giả: Phạm Tuyết Trinh<br><br>Thể loại: Ngôn Tình<br><br>Giới thiệu:<br><br>Lý Y Nhiên là đại tiểu thư nhà họ Lý, mẹ mất sớm, ba lấy thêm mẹ kế, còn có một đứa con gái riêng bằng tuổi với cô. Cô thường xuyên bị ngược đãi và bị bắt nạt, sau khi ba cô mất, để có thể dành được tài sản gia đình, cô đã kí hợp đồng hôn nhân tạm thời với Nhan Lục Tần - Chủ của một công ty lớn, anh cũng đồng ý kí hợp đồng với cô để tránh bị ba mẹ ép hôn với nhà họ Lưu. Tạm thời họ sống chung với nha tại căn hộ riêng của Nhan Lục Tần và tình yêu ngang trái của họ bắt đầu từ đó..."}